easycv/__init__.py
easycv/collection.py
easycv/image.py
easycv/list.py
easycv/operation.py
easycv/output.py
easycv/pipeline.py
easycv/utils.py
easycv/validators.py
easycv/video.py
easycv/errors/__init__.py
easycv/errors/io.py
easycv/errors/list.py
easycv/errors/resources.py
easycv/errors/transforms.py
easycv/io/__init__.py
easycv/io/input.py
easycv/io/output.py
easycv/resources/__init__.py
easycv/resources/creator.py
easycv/resources/download.py
easycv/resources/resources.py
easycv/resources/sources/apiclient.yaml
easycv/resources/sources/colorization_zhang.yaml
easycv/resources/sources/cse-credentials.yaml
easycv/resources/sources/haar-eye-cascade.yaml
easycv/resources/sources/haar-face-cascade.yaml
easycv/resources/sources/haar-person-cascade.yaml
easycv/resources/sources/haar-smile-cascade.yaml
easycv/resources/sources/ssd-mobilenet.yaml
easycv/resources/sources/yolov3.yaml
easycv/transforms/__init__.py
easycv/transforms/base.py
easycv/transforms/color.py
easycv/transforms/detect.py
easycv/transforms/draw.py
easycv/transforms/edges.py
easycv/transforms/filter.py
easycv/transforms/morphological.py
easycv/transforms/noise.py
easycv/transforms/perspective.py
easycv/transforms/selectors.py
easycv/transforms/spatial.py
tests/__init__.py
tests/test_image.py
tests/test_list.py
tests/test_pipeline.py
easycv-0.3.0.dist-info/LICENSE.txt
easycv-0.3.0.dist-info/METADATA
easycv-0.3.0.dist-info/WHEEL
easycv-0.3.0.dist-info/top_level.txt
easycv-0.3.0.dist-info/RECORD
