Metadata-Version: 2.1
Name: easycv
Version: 0.3.0
Summary: Computer Vision made easy
Home-page: https://github.com/easycv/easycv
Author: EasyCV Developers
Author-email: easycv.developers@gmail.com
License: MIT
Download-URL: https://github.com/easycv/easycv/archive/v0.3.0.tar.gz
Keywords: easycv,computer vision,python,ai
Platform: UNKNOWN
Classifier: Intended Audience :: Developers
Classifier: Topic :: Software Development :: Build Tools
Classifier: License :: OSI Approved :: MIT License
Classifier: Programming Language :: Python :: 3
Classifier: Programming Language :: Python :: 3.5
Classifier: Programming Language :: Python :: 3.6
Classifier: Programming Language :: Python :: 3.7
Classifier: Programming Language :: Python :: 3.8
Requires-Python: >=3.5
Requires-Dist: numpy
Requires-Dist: pillow
Requires-Dist: requests
Requires-Dist: matplotlib
Requires-Dist: opencv-python
Requires-Dist: scikit-image
Requires-Dist: ray
Requires-Dist: pyzbar
Requires-Dist: tqdm
Requires-Dist: pyyaml
Requires-Dist: color-transfer
Requires-Dist: pyqt5 (==5.14.2)
Requires-Dist: sklearn
